aws_framework/__init__.py
aws_framework/_apprunner.py
aws_framework/_apprunnerTypes.py
aws_framework/_bucket.py
aws_framework/_ci_types.py
aws_framework/_cloudflare.py
aws_framework/_cognito.py
aws_framework/_config.py
aws_framework/_decorators.py
aws_framework/_exceptions.py
aws_framework/_fmt.py
aws_framework/_github.py
aws_framework/_swagger.py
aws_framework/_types.py
aws_framework/api.py
aws_framework/client.py
aws_framework/data.py
aws_framework/odm.py
aws_framework/repository.py
aws_framework/scripts/containers/codeserver/Dockerfile
aws_framework/scripts/containers/express/.git/COMMIT_EDITMSG
aws_framework/scripts/containers/express/.git/HEAD
aws_framework/scripts/containers/express/.git/config
aws_framework/scripts/containers/express/.git/description
aws_framework/scripts/containers/express/.git/hooks/applypatch-msg.sample
aws_framework/scripts/containers/express/.git/hooks/commit-msg.sample
aws_framework/scripts/containers/express/.git/hooks/fsmonitor-watchman.sample
aws_framework/scripts/containers/express/.git/hooks/post-update.sample
aws_framework/scripts/containers/express/.git/hooks/pre-applypatch.sample
aws_framework/scripts/containers/express/.git/hooks/pre-commit.sample
aws_framework/scripts/containers/express/.git/hooks/pre-merge-commit.sample
aws_framework/scripts/containers/express/.git/hooks/pre-push.sample
aws_framework/scripts/containers/express/.git/hooks/pre-rebase.sample
aws_framework/scripts/containers/express/.git/hooks/pre-receive.sample
aws_framework/scripts/containers/express/.git/hooks/prepare-commit-msg.sample
aws_framework/scripts/containers/express/.git/hooks/push-to-checkout.sample
aws_framework/scripts/containers/express/.git/hooks/update.sample
aws_framework/scripts/containers/express/.git/index
aws_framework/scripts/containers/express/.git/info/exclude
aws_framework/scripts/containers/express/.git/logs/HEAD
aws_framework/scripts/containers/express/.git/logs/refs/heads/main
aws_framework-0.0.2.dist-info/METADATA
aws_framework-0.0.2.dist-info/WHEEL
aws_framework-0.0.2.dist-info/entry_points.txt
aws_framework-0.0.2.dist-info/RECORD
